cpilib/__init__.py
cpilib/constants.py
cpilib/cpi/__init__.py
cpilib/cpi/base_classes.py
cpilib/cpi/fr_cpi.py
cpilib/cpi/hicp.py
cpilib/data/cpi2015.xls
cpilib/data/hicp_labels.csv
cpilib/utils/__init__.py
cpilib/utils/coicop.py
cpilib/utils/eurostats.py
cpilib-0.3.1.dist-info/METADATA
cpilib-0.3.1.dist-info/WHEEL
cpilib-0.3.1.dist-info/RECORD
